trace_server/__init__.py
trace_server/html_generator.py
playwright_traceview_html-0.3.0.dist-info/LICENSE
playwright_traceview_html-0.3.0.dist-info/METADATA
playwright_traceview_html-0.3.0.dist-info/WHEEL
playwright_traceview_html-0.3.0.dist-info/entry_points.txt
playwright_traceview_html-0.3.0.dist-info/top_level.txt
playwright_traceview_html-0.3.0.dist-info/RECORD
