Metadata-Version: 2.1
Name: playwright-traceview-html
Version: 0.3.0
Summary: Interactive local HTML report and server for Playwright trace results.
Home-page: https://github.com/JK-JuLaYi/playwright-traceview-html
Author: Jaya Krishna
Author-email: jayakrishna107@gmail.com
License: MIT
Platform: UNKNOWN
Requires-Python: >=3.11
License-File: LICENSE
Requires-Dist: playwright (>=1.45.0)
Requires-Dist: jinja2
